[
  {
    "supplier": "mary taylor wines",
    "producer": "pascal biotteau",
    "cuvee": "anjou rouge",
    "grape_variety": "cabernet franc",
    "style": "red",
    "vintage": "2018",
    "btl_size": 750,
    "btls_case": 12,
    "cost_case": "$ -",
    "appellation": "anjou",
    "app_ii": "anjou",
    "region": "loire valley",
    "country": "france",
    "classification": "-",
    "abv": "14.1%",
    "other": ""
  },
  {
    "supplier": "mary taylor wines",
    "producer": "odile delpon",
    "cuvee": "cahors",
    "grape_variety": "malbec",
    "style": "red",
    "vintage": "2017",
    "btl_size": 750,
    "btls_case": 12,
    "cost_case": "$ -",
    "appellation": "cahors",
    "app_ii": "cahors",
    "region": "southwest france",
    "country": "france",
    "classification": "-",
    "abv": "13.5%",
    "other": ""
  },
  {
    "supplier": "mary taylor wines",
    "producer": "lúcia ferreira",
    "cuvee": "dão",
    "grape_variety": "encruzado",
    "style": "white",
    "vintage": "2018",
    "btl_size": 750,
    "btls_case": 12,
    "cost_case": "$ -",
    "appellation": "dão",
    "app_ii": "dão",
    "region": "terras do dão",
    "country": "portugal",
    "classification": "-",
    "abv": "14.0%",
    "other": ""
  },
  {
    "supplier": "mary taylor wines",
    "producer": "marine descombe",
    "cuvee": "beaujolais-villages",
    "grape_variety": "gamay",
    "style": "red",
    "vintage": "2018",
    "btl_size": 750,
    "btls_case": 12,
    "cost_case": "$ -",
    "appellation": "beaujolais-villages",
    "app_ii": "beaujolais",
    "region": "burgundy",
    "country": "france",
    "classification": "-",
    "abv": "13.0%",
    "other": ""
  },
  {
    "supplier": "la caravelle",
    "producer": "la caravelle",
    "cuvee": "blanc de blancs",
    "grape_variety": "chardonnay",
    "style": "sparkling",
    "vintage": "nv",
    "btl_size": 750,
    "btls_case": 12,
    "cost_case": "$ -",
    "appellation": "champagne",
    "app_ii": "champagne",
    "region": "champagne",
    "country": "france",
    "classification": "brut",
    "abv": "12.0%",
    "other": ""
  },
  {
    "supplier": "la caravelle",
    "producer": "la caravelle",
    "cuvee": "cuvée niña",
    "grape_variety": "chardonnay",
    "style": "sparkling",
    "vintage": "nv",
    "btl_size": 750,
    "btls_case": 12,
    "cost_case": "$ -",
    "appellation": "champagne",
    "app_ii": "champagne",
    "region": "champagne",
    "country": "france",
    "classification": "brut",
    "abv": "12.0%",
    "other": ""
  },
  {
    "supplier": "la caravelle",
    "producer": "la caravelle",
    "cuvee": "cuvée niña",
    "grape_variety": "chardonnay",
    "style": "sparkling",
    "vintage": "nv",
    "btl_size": 350,
    "btls_case": 12,
    "cost_case": "$ -",
    "appellation": "champagne",
    "app_ii": "champagne",
    "region": "champagne",
    "country": "france",
    "classification": "brut",
    "abv": "12.0%",
    "other": ""
  },
  {
    "supplier": "la caravelle",
    "producer": "la caravelle",
    "cuvee": "rosé",
    "grape_variety": "chardonnay",
    "style": "sparkling rosé",
    "vintage": "nv",
    "btl_size": 750,
    "btls_case": 12,
    "cost_case": "$ -",
    "appellation": "champagne",
    "app_ii": "champagne",
    "region": "champagne",
    "country": "france",
    "classification": "brut",
    "abv": "12.0%",
    "other": ""
  },
  {
    "supplier": "la caravelle",
    "producer": "la caravelle",
    "cuvee": "listrac-médoc",
    "grape_variety": "merlot",
    "style": "red",
    "vintage": "2015",
    "btl_size": 750,
    "btls_case": 12,
    "cost_case": "$ -",
    "appellation": "listrac-médoc",
    "app_ii": "listrac-médoc",
    "region": "bordeaux",
    "country": "france",
    "classification": "",
    "abv": "14.0%",
    "other": ""
  },
  {
    "supplier": "iota",
    "producer": "iota",
    "cuvee": "pelos sandberg vineyard",
    "grape_variety": "pinot noir",
    "style": "red",
    "vintage": "2015",
    "btl_size": 750,
    "btls_case": 12,
    "cost_case": "$ -",
    "appellation": "eola-amity hills",
    "app_ii": "willamette valley",
    "region": "oregon",
    "country": "usa",
    "classification": "",
    "abv": "13.5%",
    "other": ""
  },
  {
    "supplier": "authentique",
    "producer": "authentique",
    "cuvee": "the corridor",
    "grape_variety": "pinot noir",
    "style": "red",
    "vintage": "2015",
    "btl_size": 750,
    "btls_case": 12,
    "cost_case": "$ -",
    "appellation": "eola-amity hills",
    "app_ii": "willamette valley",
    "region": "oregon",
    "country": "usa",
    "classification": "",
    "abv": "13.9%",
    "other": ""
  },
  {
    "supplier": "authentique",
    "producer": "authentique",
    "cuvee": "vitae-springs - amphorae & oak",
    "grape_variety": "pinot noir",
    "style": "red",
    "vintage": "2015",
    "btl_size": 750,
    "btls_case": 12,
    "cost_case": "$ -",
    "appellation": "willamette valley",
    "app_ii": "willamette valley",
    "region": "oregon",
    "country": "usa",
    "classification": "",
    "abv": "13.6%",
    "other": "amphora"
  },
  {
    "supplier": "authentique",
    "producer": "authentique",
    "cuvee": "keeler estate",
    "grape_variety": "pinot noir",
    "style": "red",
    "vintage": "2015",
    "btl_size": 750,
    "btls_case": 12,
    "cost_case": "$ -",
    "appellation": "eola-amity hills",
    "app_ii": "willamette valley",
    "region": "oregon",
    "country": "usa",
    "classification": "",
    "abv": "13.4%",
    "other": "biodynamic, organic"
  },
  {
    "supplier": "authentique",
    "producer": "authentique",
    "cuvee": "keeler estate",
    "grape_variety": "chardonnay",
    "style": "white",
    "vintage": "2016",
    "btl_size": 750,
    "btls_case": 12,
    "cost_case": "$ -",
    "appellation": "eola-amity hills",
    "app_ii": "willamette valley",
    "region": "oregon",
    "country": "usa",
    "classification": "",
    "abv": "12.9%",
    "other": "orange, biodynamic, organic"
  },
  {
    "supplier": "authentique",
    "producer": "authentique",
    "cuvee": "leisure - skin contact",
    "grape_variety": "pinot gris",
    "style": "rosé",
    "vintage": "2017",
    "btl_size": 750,
    "btls_case": 12,
    "cost_case": "$ -",
    "appellation": "eola-amity hills",
    "app_ii": "willamette valley",
    "region": "oregon",
    "country": "usa",
    "classification": "",
    "abv": "13.6%",
    "other": "biodynamic, organic"
  },
  {
    "supplier": "malivoire",
    "producer": "malivoire",
    "cuvee": "estate grown chardonnay",
    "grape_variety": "chardonnay",
    "style": "white",
    "vintage": "2018",
    "btl_size": 750,
    "btls_case": 12,
    "cost_case": "$ -",
    "appellation": "beamsville bench",
    "app_ii": "niagra",
    "region": "ontario",
    "country": "canada",
    "classification": "",
    "abv": "12.5%",
    "other": ""
  },
  {
    "supplier": "malivoire",
    "producer": "malivoire",
    "cuvee": "small lot gamay",
    "grape_variety": "gamay",
    "style": "red",
    "vintage": "2018",
    "btl_size": 750,
    "btls_case": 12,
    "cost_case": "$ -",
    "appellation": "niagra escarpment",
    "app_ii": "niagra",
    "region": "ontario",
    "country": "canada",
    "classification": "",
    "abv": "12.0%",
    "other": ""
  },
  {
    "supplier": "malivoire",
    "producer": "malivoire",
    "cuvee": "courtney gamay",
    "grape_variety": "gamay",
    "style": "red",
    "vintage": "2017",
    "btl_size": 750,
    "btls_case": 12,
    "cost_case": "$ -",
    "appellation": "beamsville bench",
    "app_ii": "niagra",
    "region": "ontario",
    "country": "canada",
    "classification": "",
    "abv": "13.0%",
    "other": ""
  },
  {
    "supplier": "malivoire",
    "producer": "malivoire",
    "cuvee": "small lot pinot",
    "grape_variety": "pinot noir",
    "style": "red",
    "vintage": "2018",
    "btl_size": 750,
    "btls_case": 12,
    "cost_case": "$ -",
    "appellation": "beamsville bench",
    "app_ii": "niagra",
    "region": "ontario",
    "country": "canada",
    "classification": "",
    "abv": "12.0%",
    "other": ""
  },
  {
    "supplier": "rosehall run",
    "producer": "rosehall run",
    "cuvee": "rosehall vineyard",
    "grape_variety": "chardonnay",
    "style": "white",
    "vintage": "2018",
    "btl_size": 750,
    "btls_case": 12,
    "cost_case": "$ -",
    "appellation": "prince edward county",
    "app_ii": "prince edward county",
    "region": "ontario",
    "country": "canada",
    "classification": "",
    "abv": "12.5%",
    "other": ""
  },
  {
    "supplier": "rosehall run",
    "producer": "rosehall run",
    "cuvee": "rosehall vineyard",
    "grape_variety": "pinot noir",
    "style": "red",
    "vintage": "2018",
    "btl_size": 750,
    "btls_case": 12,
    "cost_case": "$ -",
    "appellation": "prince edward county",
    "app_ii": "prince edward county",
    "region": "ontario",
    "country": "canada",
    "classification": "",
    "abv": "12.0%",
    "other": ""
  },
  {
    "supplier": "rosehall run",
    "producer": "rosehall run",
    "cuvee": "ceremony blanc de blancs",
    "grape_variety": "chardonnay",
    "style": "sparkling",
    "vintage": "nv",
    "btl_size": 750,
    "btls_case": 12,
    "cost_case": "$ -",
    "appellation": "prince edward county",
    "app_ii": "prince edward county",
    "region": "ontario",
    "country": "canada",
    "classification": "brut",
    "abv": "12.2%",
    "other": ""
  },
  {
    "supplier": "rosehall run",
    "producer": "rosehall run",
    "cuvee": "pixie",
    "grape_variety": "vidal",
    "style": "sparkling rosé",
    "vintage": "nv",
    "btl_size": 750,
    "btls_case": 12,
    "cost_case": "$ -",
    "appellation": "ontario",
    "app_ii": "ontario",
    "region": "ontario",
    "country": "canada",
    "classification": "",
    "abv": "11.7%",
    "other": ""
  },
  {
    "supplier": "madrigal family winery",
    "producer": "madrigal family winery",
    "cuvee": "petite sirah",
    "grape_variety": "petite sirah",
    "style": "red",
    "vintage": "2014",
    "btl_size": 750,
    "btls_case": 12,
    "cost_case": "$ -",
    "appellation": "napa valley",
    "app_ii": "napa valley",
    "region": "california",
    "country": "usa",
    "classification": "",
    "abv": "14.5%",
    "other": ""
  },
  {
    "supplier": "madrigal family winery",
    "producer": "madrigal family winery",
    "cuvee": "zinfandel",
    "grape_variety": "zinfandel",
    "style": "red",
    "vintage": "2014",
    "btl_size": 750,
    "btls_case": 12,
    "cost_case": "$ -",
    "appellation": "napa valley",
    "app_ii": "napa valley",
    "region": "california",
    "country": "usa",
    "classification": "",
    "abv": "14.8%",
    "other": ""
  },
  {
    "supplier": "",
    "producer": "",
    "cuvee": "",
    "grape_variety": "",
    "style": "",
    "vintage": "",
    "btl_size": "",
    "btls_case": "",
    "cost_case": "",
    "appellation": "",
    "app_ii": "",
    "region": "",
    "country": "",
    "classification": "",
    "abv": "",
    "other": ""
  },
  {
    "supplier": "authentique, keeler estate chardonnay, willamette valley 2016",
    "producer": "",
    "cuvee": "",
    "grape_variety": "",
    "style": "",
    "vintage": "",
    "btl_size": "",
    "btls_case": "",
    "cost_case": "",
    "appellation": "",
    "app_ii": "",
    "region": "",
    "country": "",
    "classification": "",
    "abv": "",
    "other": ""
  }
]